[
     {
          "id": 1,
          "name": "Terrence S. Mendez",
          "feedback": "This theme works very well with page builder and has extra options on it, very professional template with all the options you need ❤️",
          "rating": 4,
          "img": "https://img.freepik.com/free-photo/indoor-picture-cheerful-handsome-young-man-having-folded-hands-looking-directly-smiling-sincerely-wearing-casual-clothes_176532-10257.jpg?size=626&ext=jpg&ga=GA1.1.824354190.1681013433&semt=ais",
          "quality": "Web Developer"
     },
     {
          "id": 2,
          "name": "Terrence S. Mendez",
          "feedback": "Amazing theme, very flexible. I really like the page builder in this item, easy to use and custom. Highly recommended!❤️",
          "rating": 2,
          "quality": "Web Designer",
          "img": "https://img.freepik.com/free-photo/handsome-businessman-suit-glasses-cross-arms-chest-look_176420-21750.jpg?q=10&h=200"
     },
     {
          "id": 3,
          "name": "Terrence S. Mendez",
          "feedback": "This theme works very well with page builder and has extra options on it, very professional template with all the options you need ❤️",
          "rating": 3.5,
          "quality": "MERN stack Developer",
          "img": "https://blueskytechmage.com/minimog/media/blueskytechco/testimonial/h/2/h2_testimonial_03.jpeg"
     },
     {
          "id": 4,
          "name": "Terrence S. Mendez",
          "feedback": "This theme works very well with page builder and has extra options on it, very professional template with all the options you need ❤️❤️",
          "rating": 4.5,
          "quality": "Senior Developer  ",
          "img": "https://blueskytechmage.com/minimog/media/blueskytechco/testimonial/h/2/h2_testimonial_02.jpeg"
     }
]